amun/__init__.py
amun/lib.py
amun/swagger_client/__init__.py
amun/swagger_client/api_client.py
amun/swagger_client/configuration.py
amun/swagger_client/exceptions.py
amun/swagger_client/rest.py
amun/swagger_client/amun/__init__.py
amun/swagger_client/amun/debug_api.py
amun/swagger_client/amun/inspection_api.py
amun/swagger_client/amun/service_api.py
amun/swagger_client/models/__init__.py
amun/swagger_client/models/inspection_build_log_response.py
amun/swagger_client/models/inspection_generate_dockerfile_response.py
amun/swagger_client/models/inspection_job_batch_size_response.py
amun/swagger_client/models/inspection_job_log_response.py
amun/swagger_client/models/inspection_job_log_response_log.py
amun/swagger_client/models/inspection_job_result_response.py
amun/swagger_client/models/inspection_job_result_response_result.py
amun/swagger_client/models/inspection_response.py
amun/swagger_client/models/inspection_response_error.py
amun/swagger_client/models/inspection_specification.py
amun/swagger_client/models/inspection_specification_build.py
amun/swagger_client/models/inspection_specification_build_requests.py
amun/swagger_client/models/inspection_specification_build_requests_hardware.py
amun/swagger_client/models/inspection_specification_environment.py
amun/swagger_client/models/inspection_specification_files.py
amun/swagger_client/models/inspection_specification_python.py
amun/swagger_client/models/inspection_specification_response.py
amun/swagger_client/models/inspection_specification_run.py
amun/swagger_client/models/inspection_specification_run_requests.py
amun/swagger_client/models/inspection_specification_run_requests_hardware.py
amun/swagger_client/models/inspection_status.py
amun/swagger_client/models/inspection_status_build.py
amun/swagger_client/models/inspection_status_response.py
amun/swagger_client/models/version_response.py
amun-0.5.0.dist-info/METADATA
amun-0.5.0.dist-info/RECORD
amun-0.5.0.dist-info/WHEEL
amun-0.5.0.dist-info/entry_points.txt
amun-0.5.0.dist-info/top_level.txt
