Metadata-Version: 2.1
Name: amun
Version: 0.5.0
Summary: A CLI tool and library for interacting with Amun
Home-page: UNKNOWN
Author: Fridolin Pokorny
Author-email: fridolin@redhat.com
License: GPLv3+
Platform: UNKNOWN
Requires-Dist: certifi
Requires-Dist: six
Requires-Dist: python-dateutil
Requires-Dist: setuptools
Requires-Dist: urllib3
